{
  "students": [
    {
      "name": "adilet",
      "lastname": "atambaev",
      "number": "0550339001",
      "weekKpi": "100",
      "monthKpi": "100",
      "id": 1
    },
    {
      "name": "Adilet",
      "lastname": "Atambaev",
      "number": "0550339001",
      "weekKpi": "100",
      "monthKpi": "100",
      "id": 2
    },
    {
      "name": "Adilet",
      "lastname": "Atambaev",
      "number": "0550339001",
      "weekKpi": "100",
      "monthKpi": "100",
      "id": 3
    }
  ]
}